ps2/p2/b4/main-b4.v
/* main-b3-functions-mem.v */

module main_b4();
    parameter BUSW=32;
    parameter PSRW=5;
    parameter MINDW=12; //12-bit memory index
    parameter MWORDS=4096; //2**12
    parameter RINDW=4; //4-bit register bank index
    parameter RWORDS=16; //2**4
    parameter IRW=BUSW;
    parameter IR_DSTIND=0;
    parameter IR_SRCIND_CNT=12;
    parameter IR_SRCTYPE=27;
    parameter IR_DSTTYPE=26;
    parameter IR_CC=24;
    parameter IR_OP=28;
    parameter OPW=4; //opcode bit-width
    parameter CCW=4; //cond. code bit-width
    parameter CNTW=5; //+-16 2's comp. shift/rotate count bit-width
    parameter SRCINDW=MINDW; //src address bit-width
    parameter DSTINDW=MINDW; //dst address bit-width
    parameter REGTYPE=1'b0;
    parameter IMMTYPE=1'b1;
    parameter SMEMTYPE=REGTYPE;
    parameter DMEMTYPE=1'b1;
    parameter NOP = 4'b0000, //opcodes
              LD  = 4'b0001,
              STR = 4'b0010,
              BRA = 4'b0011,
              XOR = 4'b0100,
              ADD = 4'b0101,
              ROT = 4'b0110,
              SHF = 4'b0111,
              HLT = 4'b1000,
              CMP = 4'b1001;
    parameter CC_A = 4'b0000, //always
              CC_P = 4'b0001, //parity
              CC_E = 4'b0010, //even
              CC_C = 4'b0011, //carry
              CC_N = 4'b0100, //negative
              CC_Z = 4'b0101, //zero
              CC_NC = 4'b0110, //no carry
              CC_PO = 4'b0111; //positive
    parameter CARRY=0,
              PARITY=1,
              EVEN=2,
              NEGATIVE=3,
              ZERO=4;
    localparam EOF = -1;
    
//    reg [BUSW-1:0] Mem[MINDW-1:0]; //RAM memory- array of vectors   
//    reg [BUSW-1:0] Reg[RINDW-1:0];
    reg [BUSW-1:0] Mem[MWORDS-1:0];
    reg [BUSW-1:0] Reg[RWORDS-1:0];
    reg [IRW-1:0] IReg;
    reg [MINDW-1:0] PCntr; //program counter
    reg [PSRW-1:0] Psr;


    `define OPCODE IReg[IR_OP+OPW-1:IR_OP]
    `define CCODE  IReg[IR_CC+CCW-1:IR_CC]
    `define SRCTYPE IReg[IR_SRCTYPE]
    `define DSTTYPE IReg[IR_DSTTYPE]
    `define SRCIMM IReg[IR_SRCIND_CNT+SRCINDW-1:IR_SRCIND_CNT]
    `define SRCMIND IReg[IR_SRCIND_CNT+MINDW-1:IR_SRCIND_CNT]
    `define SRCRIND IReg[IR_SRCIND_CNT+RINDW-1:IR_SRCIND_CNT]
    `define DSTMIND IReg[IR_DSTIND+MINDW-1:IR_DSTIND]
    `define DSTRIND IReg[IR_DSTIND+RINDW-1:IR_DSTIND]
    `define SHFROTS IReg[IR_SRCIND_CNT+CNTW-1]
    `define SHFROTC IReg[IR_SRCIND_CNT+CNTW-2:IR_SRCIND_CNT]
    `define DSTREG Reg[`DSTRIND]
    `define DSTMEM Mem[`DSTMIND]
    `define SRCREG Reg[`SRCRIND]
    `define SRCMEM Mem[`SRCMIND]
    `define CAR Psr[CARRY]
    `define PAR Psr[PARITY]
    `define EVN Psr[EVEN]
    `define NEG Psr[NEGATIVE]
    `define ZER Psr[ZERO]

    reg clk;
    reg done;
    time tstart;
    
    initial begin
        $dumpfile("main-b4.vcd");
        $dumpvars;
    end
    
    initial begin:REG_INIT_BLOCK
        integer i;
        reg [MINDW-1:0] PCntrSave;

        for (i=0;i<MWORDS;i=i+1) begin
            #1 Mem[i] = {BUSW{1'b0}};
        end
        for (i=0;i<RWORDS;i=i+1) begin
            #1 Reg[i] = {BUSW{1'b0}};
        end
        Psr = {PSRW{1'b0}};
        
        //load a program into memory
        PCntr = fLoadProgram(32'b1001_0010_0100_1001_0010_0100_1001_0010);
        //PCntrSave = PCntr;
        //for (i=3; i<14; i=i+1) begin
        //    $display("Mem[%d]: %b", i, Mem[i]);
        //    #1 PCntr = PCntr + 1;
        //end
        //PCntr = PCntrSave;
        //$finish;

        
        clk = 0;
        done = 1'b0;
        $display("beginning program executing. PCntr=%d, T=%t\n", PCntr, $time);
        tstart = $time;
        forever begin
            #1 clk = !clk;
        end
    end

    //execute the next instruction
    always @(posedge clk) begin
        case (`OPCODE)
        LD:  PCntr<=fLOAD(1'b1);
        STR: PCntr<=fSTORE(1'b1); 
        BRA: PCntr<=fBRANCH(1'b1); 
        XOR: PCntr<=fXOR(1'b1);
        ADD: PCntr<=fADD(1'b1);
        ROT: PCntr<=fROTATE(1'b1);
        SHF: PCntr<=fSHIFT(1'b1);
        CMP: PCntr<=fCOMPLEMENT(1'b1);
        HLT: done<=1'b1;
        default: PCntr <= PCntr + 1; //NOP
        endcase
    end

    //load the next instruction if cpu has finished executing previous instruction
    always @(PCntr) begin
        IReg = Mem[PCntr];
        tPRINT_IREG;
    end

    always @(*) begin
        if (done) tFINISH;
    end
    
    /**************** functions ****************/


    task tFINISH;
    begin
        $display("Program execution finished.");
        $display("Last value stored: %d \tPsr: %b\nTotal runtime: %t\n\n\n", `DSTREG, Psr, $time-tstart);
        $finish;
    end
    endtask

    
    function fCOMPLEMENT;
    input foo;
    reg ret;
    begin
        if (`SRCTYPE === IMMTYPE) begin
            `DSTREG = ~{{(BUSW-SRCINDW){1'b0}},`SRCIMM}; 
            $display("taking the CMPlement of %b = %b", {{(BUSW-SRCINDW){1'b0}},`SRCIMM}, `DSTREG);
        end else begin
            `DSTREG = ~`SRCREG;
            $display("taking the CMPlement of %b = %b", `SRCREG, `DSTREG);
        end
        ret=fSETPSR(`DSTREG, 1'b0);
        fCOMPLEMENT = PCntr+1;
    end
    endfunction

    //implemented as rotate-through-carry since we have the last carry value available from Psr
    function [MINDW-1:0] fROTATE;
    input foo;
    reg carry, ret;
    reg [CNTW-2:0] Shift; //lose the upper sign bit
    integer i;
    begin
        carry=`CAR;
        if (`SHFROTS === 1'b1) begin //negative-- rotate >> right
            Shift = ((~{`SHFROTS,`SHFROTC})+1);
            $display("ROTating %b right by %d = ...", `DSTREG, Shift);
            for (i=0; i<Shift; i=i+1) begin
                {`DSTREG, carry} = {carry, `DSTREG}; 
            end
        end else begin //rotate << left
            $display("ROTating %b left by %d = ...", `DSTREG, `SHFROTC);
            for (i=0; i<`SHFROTC; i=i+1) begin
                {`DSTREG, carry} = {Reg[`DSTRIND][BUSW-2:0], carry, Reg[`DSTRIND][BUSW-1]};
            end
        end
        $display("\t...%b with carryout %b", `DSTREG, carry);
        ret=fSETPSR(`DSTREG, carry);
        fROTATE = PCntr+1;
    end
    endfunction


    function [MINDW-1:0] fSHIFT;
    input foo;
    reg carry, ret;
    reg [CNTW-2:0] Shift; //lose the upper sign bit
    begin
        if (`SHFROTS === 1'b1) begin //negative-- shift >> right (divide)
            carry = 1'b0;
            Shift = ((~{`SHFROTS,`SHFROTC})+1);
            $display("SHFting %b >> %d = ...", `DSTREG, Shift);
            `DSTREG = `DSTREG >> Shift;
        end else begin //positive-- shift << left (multiply)
            carry = Reg[`DSTRIND][BUSW-1];
            $display("SHFting %b << %d = ...", `DSTREG, `SHFROTC);
            `DSTREG = `DSTREG << `SHFROTC;
        end
        $display("\t...%b with carryout %b", `DSTREG, carry);
        ret=fSETPSR(`DSTREG, carry);
        fSHIFT = PCntr+1;
    end
    endfunction

    
    function [MINDW-1:0] fADD;
    input foo;
    reg carry,ret;
    begin
        if (`SRCTYPE === IMMTYPE) begin
            $display("ADDing %b + %b = ...", `DSTREG, {{(BUSW-SRCINDW){1'b0}},`SRCIMM});
            {carry,`DSTREG} = `DSTREG + {{(BUSW-SRCINDW){1'b0}},`SRCIMM};
        end else begin
            $display("ADDing %b + %b = ...", `DSTREG, `SRCREG);
            {carry,`DSTREG} = `DSTREG + `SRCREG;
        end
        $display("\t...%b with carryout %b", `DSTREG, carry);
        ret=fSETPSR(`DSTREG, carry);
        fADD = PCntr+1;
    end
    endfunction
   
    
    function [MINDW-1:0] fXOR;
    input foo;
    reg ret;
    begin
        if (`SRCTYPE === IMMTYPE) begin
            $display("XORing %b xor %b = ...", `DSTREG, {{(BUSW-SRCINDW){1'b0}},`SRCIMM});
            `DSTREG = `DSTREG ^ {{(BUSW-SRCINDW){1'b0}},`SRCIMM};
        end else begin
            $display("XORing %b xor %b = ...",`DSTREG, `SRCREG);
            `DSTREG = `DSTREG ^ `SRCREG;
        end
        $display("\t...%b", `DSTREG);
        ret=fSETPSR(`DSTREG, 1'b0);
        fXOR = PCntr+1;
    end
    endfunction
    

    function [MINDW-1:0] fBRANCH;
    input foo;
    begin
        case (`CCODE)
        CC_C:  fBRANCH = (`CAR === 1'b1 ? `DSTMIND : PCntr+1);
        CC_NC: fBRANCH = (`CAR === 1'b0 ? `DSTMIND : PCntr+1);
        CC_P:  fBRANCH = (`PAR === 1'b1 ? `DSTMIND : PCntr+1);
        CC_E:  fBRANCH = (`EVN === 1'b1 ? `DSTMIND : PCntr+1);
        CC_N:  fBRANCH = (`NEG === 1'b1 ? `DSTMIND : PCntr+1);
        CC_PO: fBRANCH = (`NEG === 1'b0 ? `DSTMIND : PCntr+1);
        CC_Z:  fBRANCH = (`ZER === 1'b1 ? `DSTMIND : PCntr+1);
        default:  fBRANCH = `DSTMIND; //CC_A
        endcase
        $display("encountered Branch. Next PCntr: %d", fBRANCH);
    end
    endfunction

    
    function [MINDW-1:0] fSTORE;
    input foo;
    begin
        if (`SRCTYPE === IMMTYPE) begin
            `DSTMEM = {{(BUSW-SRCINDW){1'b0}},`SRCIMM}; //interpret index as literal value
            $display("Storing IMMVAL %b into memory slot %d", {{(BUSW-SRCINDW){1'b0}},`SRCIMM}, `DSTMIND);
        end else begin
            `DSTMEM = `SRCREG;
            $display("Loading REGVAL %b into memory slot %d", `SRCREG, `DSTMIND);
        end 
        Psr = {PSRW{1'b0}};
        fSTORE = PCntr + 1;
    end
    endfunction
   
    
    function [MINDW-1:0] fLOAD;
    input foo;
    reg ret;
    begin   
        if (`SRCTYPE === IMMTYPE) begin
            `DSTREG = {{(BUSW-SRCINDW){1'b0}},`SRCIMM}; //interpret index as literal value
            $display("Loading IMMVAL %b into register %d", {{(BUSW-SRCINDW){1'b0}},`SRCIMM}, `DSTRIND);
        end else begin
            `DSTREG = `SRCMEM;
            $display("Loading MEMVAL %b into register %d", `SRCMEM, `DSTRIND);
        end 
        ret=fSETPSR(`DSTREG, 1'b0); 
        fLOAD = PCntr + 1;
    end
    endfunction

    
    function fSETPSR;
    input reg [BUSW-1:0] Val;
    input carry;
    begin
        `CAR = carry; //Carry
        `PAR = fPARITY(Val); //Parity
        `EVN = ~Val[0]; //Even
        `NEG = Val[BUSW-1]; //Negative
        `ZER = (Val === {BUSW{1'b0}} ? 1'b1 : 1'b0); //Zero
        fSETPSR = 1'b1;
        $display("Psr for Val %b: Carry=%b, Parity=%b, Even=%b, Negative=%b, Zero=%b", Val, `CAR, `PAR, `EVN, `NEG, `ZER);
    end
    endfunction


    function [0:0] fPARITY;
    input [BUSW-1:0] Val;
    integer i;
    begin
        fPARITY=1'b0;
        for(i=0; i<BUSW; i=i+1) begin
            if (Val[i]) begin
                fPARITY = ~fPARITY;
            end
        end
    end
    endfunction


    function [MINDW-1:0] fLoadProgram;
    input reg [BUSW-1:0] Arg;
    begin
        /*Mem[0] = Arg; //arbitrary number between 0 and BUSW-1.
        Mem[1] = 0; //initialize location to store result.
        Mem[2] = {LD,SMEMTYPE,REGTYPE,{(CCW-2){1'b0}},fFitSrcInd(0),fFitDstInd(0)};
        Mem[3] = {LD,IMMTYPE,REGTYPE,{(CCW-2){1'b0}},fFitSrcInd(0),fFitDstInd(1)};
        Mem[4] = {SHF,IMMTYPE,REGTYPE,{(CCW-2){1'b0}},fFitSrcInd(1),fFitDstInd(0)};
        Mem[5] = {BRA,CC_NC,{SRCINDW{1'b0}},fFitDstInd(7)};
        Mem[6] = {ADD,IMMTYPE,REGTYPE,{(CCW-2){1'b0}},fFitSrcInd(1),fFitDstInd(1)};
        Mem[7] = {BRA,CC_Z,{SRCINDW{1'b0}},fFitDstInd(9)};
        Mem[8] = {BRA,CC_A,{SRCINDW{1'b0}},fFitDstInd(4)};
        Mem[9] = {STR,REGTYPE,DMEMTYPE,{(CCW-2){1'b0}},fFitSrcInd(1),fFitDstInd(1)};
        Mem[10] = {HLT,REGTYPE,DMEMTYPE,{(CCW-2){1'b0}},fFitSrcInd(1),fFitDstInd(1)};
        fLoadProgram=2;*/
        $display("initializing program. T=%t", $time);
        Mem[0] = Arg;
        Mem[1] = 0;
        Mem[2] = {BUSW{1'b1}};
        Mem[3] = {LD, SMEMTYPE, REGTYPE, {(CCW-2){1'b0}}, fFitSrcInd(0), fFitDstInd(0)};
        Mem[4] = {LD, SMEMTYPE, REGTYPE, {(CCW-2){1'b0}}, fFitSrcInd(1), fFitDstInd(1)};
        Mem[5] = {LD, SMEMTYPE, REGTYPE, {(CCW-2){1'b0}}, fFitSrcInd(2), fFitDstInd(2)};
        Mem[6] = {SHF, IMMTYPE, REGTYPE, {(CCW-2){1'b0}}, 12'b0000_0000_0001, fFitDstInd(0)};
        Mem[7] = {BRA, CC_NC, fFitSrcInd(0), fFitDstInd(9)};
        Mem[8] = {ADD, IMMTYPE, REGTYPE, {(CCW-2){1'b0}}, fFitSrcInd(1), fFitDstInd(1)};
        Mem[9] = {SHF, IMMTYPE, REGTYPE, {(CCW-2){1'b0}}, {12{1'b1}}, fFitDstInd(2)};
        Mem[10] = {BRA, CC_Z, fFitSrcInd(0), fFitDstInd(12)};
        Mem[11] = {BRA, CC_A, fFitSrcInd(0), fFitDstInd(6)};
        Mem[12] = {STR, REGTYPE, DMEMTYPE, {(CCW-2){1'b0}}, fFitSrcInd(1), fFitDstInd(1)};
        Mem[13] = {HLT, REGTYPE, DMEMTYPE, {(CCW-2){1'b0}}, fFitSrcInd(1), fFitDstInd(1)};

        /*Mem[0] = 32'b1001_0010_0100_1001_0010_0100_1001_0010;
        Mem[1] = 32'b0000_0000_0000_0000_0000_0000_0000_0000;
        Mem[2] = 32'b1111_1111_1111_1111_1111_1111_1111_1111;
        Mem[3] = 32'b0001_0000_0000_0000_0001_0000_0000_0001;
        Mem[4] = 32'b0001_0000_0000_0000_0010_0000_0000_0010;
        Mem[5] = 32'b0001_0000_0000_0000_0011_0000_0000_0011;
        Mem[6] = 32'b0111_1000_0000_0000_0001_0000_0000_0000;
        Mem[7] = 32'b0011_0110_0000_0000_0000_0000_0000_0000;
        Mem[8] = 32'b0101_1000_0000_0000_0001_0000_0000_0001;
        Mem[9] = 32'b0111_1000_1111_1111_1111_0000_0000_0010;
        Mem[10] = 32'b0011_0101_0000_0000_0000_0000_0000_1100;
        Mem[11] = 32'b0011_0000_0000_0000_0000_0000_0000_0110;
        Mem[12] = 32'b0010_0100_0000_0000_0001_0000_0000_0001;
        Mem[13] = 32'b1000_0100_0000_0000_0001_0000_0000_0001;*/
        fLoadProgram = 3;
        $display("done initializing program. T=%t", $time);
    end
    endfunction


    function [SRCINDW-1:0] fFitSrcInd;
    input integer I;
    begin
        fFitSrcInd=I;
    end
    endfunction


    function [DSTINDW-1:0] fFitDstInd;
    input integer I;
    begin
        fFitDstInd=I;
    end
    endfunction


    task tPRINT_IREG;
    begin   
        $display("t=%t, \tPC=%d, \tnext instruction:", $time, PCntr);
        case(`OPCODE)
        LD: begin
            if (`SRCTYPE === IMMTYPE) begin
                $display("LD R%d \'%b\'\n", `DSTRIND, `SRCIMM);
            end else begin
                $display("LD R%d M%d (%b)\n", `DSTRIND, `SRCMIND, `SRCMEM);
            end
            end
        STR: begin
            if (`SRCTYPE === IMMTYPE) begin
                $display("STR M%d \'%d\'\n", `DSTMIND, `SRCIMM);
            end else begin
                $display("STR M%d R%d (%d)\n", `DSTMIND, `SRCRIND, `SRCREG);
            end
            end
        BRA: begin
            case (`CCODE)
            CC_A: $display("BRA: <always> GOTO M%d\n", `DSTMIND);
            CC_P: $display("BRA: <if parity> GOTO M%d\n", `DSTMIND);
            CC_E: $display("BRA: <if even> GOTO M%d\n", `DSTMIND);
            CC_C: $display("BRA: <if carry> GOTO M%d\n", `DSTMIND);
            CC_N: $display("BRA: <if negative> GOTO M%d\n", `DSTMIND);
            CC_Z: $display("BRA: <if zero> GOTO M%d\n", `DSTMIND);
            CC_NC: $display("BRA: <if no carry> GOTO M%d\n", `DSTMIND);
            CC_PO: $display("BRA: <if positive> GOTO M%d\n", `DSTMIND);
            endcase
            end
        XOR: begin
            if (`SRCTYPE === IMMTYPE) begin
                $display("XOR R%d (%d) \'%d\'\n", `DSTRIND, `DSTREG, `SRCIMM);
            end else begin
                $display("XOR R%d (%d) R%d (%d)\n", `DSTRIND, `DSTREG, `SRCRIND, `SRCREG);
            end
            end
        ADD: begin
            if (`SRCTYPE === IMMTYPE) begin
                $display("ADD R%d \'%d\'\n", `DSTRIND, `SRCIMM);
            end else begin
                $display("ADD R%d (%d) R%d (%d)\n", `DSTRIND, `DSTREG, `SRCRIND, `SRCREG);
            end
            end
        ROT: begin:DISP_ROT
            reg [CNTW-2:0] Shift;
            if (`SHFROTS === 1'b1) begin //negative-- right (divide)
                Shift = (~{`SHFROTS,`SHFROTC})+1;
                $display("ROT R%d (%d) right %d\n", `DSTRIND, `DSTREG, Shift);
            end else begin
                $display("ROT R%d (%d) left %d\n", `DSTRIND, `DSTREG, `SHFROTC);
            end
            end
        SHF: begin:DIST_SHF
            reg [CNTW-2:0] Shift;
            if (`SHFROTS === 1'b1) begin
                Shift = (~{`SHFROTS,`SHFROTC})+1;
                $display("SHF R%d (%d) right %d\n", `DSTRIND, `DSTREG, Shift);
            end else begin
                $display("SHF R%d (%d) left %d\n", `DSTRIND, `DSTREG, `SHFROTC);
            end
            end
        CMP: begin
            if (`SRCTYPE === IMMTYPE) begin
                $display("CMP R%d \'%d\'\n", `DSTRIND, `SRCIMM);
            end else begin
                $display("CMP R%d R%d (%d)\n", `DSTRIND, `SRCRIND, `SRCREG);
            end
            end
        HLT: begin
            $display("HLT\n");
            end
        NOP: begin
            $display("NOP\n");
            end
        default: $display("No match. IReg contains %b", IReg);
        endcase
    end
    endtask

endmodule

ps2/p2-b/src/b4/main-b4.vcd
$date
	Sat Oct 10 13:12:17 2015
$end
$version
	QuestaSim Version 6.5f
$end
$timescale
	1fs
$end
$scope module main_b4 $end
$var parameter 32 ! BUSW $end
$var parameter 32 " PSRW $end
$var parameter 32 # MINDW $end
$var parameter 32 $ MWORDS $end
$var parameter 32 % RINDW $end
$var parameter 32 & RWORDS $end
$var parameter 32 ' IRW $end
$var parameter 32 ( IR_DSTIND $end
$var parameter 32 ) IR_SRCIND_CNT $end
$var parameter 32 * IR_SRCTYPE $end
$var parameter 32 + IR_DSTTYPE $end
$var parameter 32 , IR_CC $end
$var parameter 32 - IR_OP $end
$var parameter 32 . OPW $end
$var parameter 32 / CCW $end
$var parameter 32 0 CNTW $end
$var parameter 32 1 SRCINDW $end
$var parameter 32 2 DSTINDW $end
$var parameter 1 3 REGTYPE $end
$var parameter 1 4 IMMTYPE $end
$var parameter 1 5 SMEMTYPE $end
$var parameter 1 6 DMEMTYPE $end
$var parameter 4 7 NOP $end
$var parameter 4 8 LD $end
$var parameter 4 9 STR $end
$var parameter 4 : BRA $end
$var parameter 4 ; XOR $end
$var parameter 4 < ADD $end
$var parameter 4 = ROT $end
$var parameter 4 > SHF $end
$var parameter 4 ? HLT $end
$var parameter 4 @ CMP $end
$var parameter 4 A CC_A $end
$var parameter 4 B CC_P $end
$var parameter 4 C CC_E $end
$var parameter 4 D CC_C $end
$var parameter 4 E CC_N $end
$var parameter 4 F CC_Z $end
$var parameter 4 G CC_NC $end
$var parameter 4 H CC_PO $end
$var parameter 32 I CARRY $end
$var parameter 32 J PARITY $end
$var parameter 32 K EVEN $end
$var parameter 32 L NEGATIVE $end
$var parameter 32 M ZERO $end
$var parameter 32 N EOF $end
$var reg 32 O IReg [31:0] $end
$var reg 12 P PCntr [11:0] $end
$var reg 5 Q Psr [4:0] $end
$var reg 1 R clk $end
$var reg 1 S done $end
$var time 64 T tstart $end
$scope begin REG_INIT_BLOCK $end
$var integer 32 U i $end
$var reg 12 V PCntrSave [11:0] $end
$upscope $end
$scope task tFINISH $end
$upscope $end
$scope function fCOMPLEMENT $end
$var reg 1 W fCOMPLEMENT $end
$var reg 1 X foo $end
$var reg 1 Y ret $end
$upscope $end
$scope function fROTATE $end
$var reg 12 Z fROTATE [11:0] $end
$var reg 1 [ foo $end
$var reg 1 \ carry $end
$var reg 1 ] ret $end
$var reg 4 ^ Shift [3:0] $end
$var integer 32 _ i $end
$upscope $end
$scope function fSHIFT $end
$var reg 12 ` fSHIFT [11:0] $end
$var reg 1 a foo $end
$var reg 1 b carry $end
$var reg 1 c ret $end
$var reg 4 d Shift [3:0] $end
$upscope $end
$scope function fADD $end
$var reg 12 e fADD [11:0] $end
$var reg 1 f foo $end
$var reg 1 g carry $end
$var reg 1 h ret $end
$upscope $end
$scope function fXOR $end
$var reg 12 i fXOR [11:0] $end
$var reg 1 j foo $end
$var reg 1 k ret $end
$upscope $end
$scope function fBRANCH $end
$var reg 12 l fBRANCH [11:0] $end
$var reg 1 m foo $end
$upscope $end
$scope function fSTORE $end
$var reg 12 n fSTORE [11:0] $end
$var reg 1 o foo $end
$upscope $end
$scope function fLOAD $end
$var reg 12 p fLOAD [11:0] $end
$var reg 1 q foo $end
$var reg 1 r ret $end
$upscope $end
$scope function fSETPSR $end
$var reg 1 s fSETPSR $end
$var reg 32 t Val [31:0] $end
$var reg 1 u carry $end
$upscope $end
$scope function fPARITY $end
$var reg 1 v fPARITY [0:0] $end
$var reg 32 w Val [31:0] $end
$var integer 32 x i $end
$upscope $end
$scope function fLoadProgram $end
$var reg 12 y fLoadProgram [11:0] $end
$var reg 32 z Arg [31:0] $end
$upscope $end
$scope function fFitSrcInd $end
$var reg 12 { fFitSrcInd [11:0] $end
$var integer 32 | I $end
$upscope $end
$scope function fFitDstInd $end
$var reg 12 } fFitDstInd [11:0] $end
$var integer 32 ~ I $end
$upscope $end
$scope task tPRINT_IREG $end
$scope begin DISP_ROT $end
$var reg 4 !! Shift [3:0] $end
$upscope $end
$scope begin DIST_SHF $end
$var reg 4 "! Shift [3:0] $end
$upscope $end
$upscope $end
$upscope $end
$enddefinitions $end
#0
$dumpvars
b100000 !
b101 "
b1100 #
b1000000000000 $
b100 %
b10000 &
b100000 '
b0 (
b1100 )
b11011 *
b11010 +
b11000 ,
b11100 -
b100 .
b100 /
b101 0
b1100 1
b1100 2
b0 3
b1 4
b0 5
b1 6
b0 7
b1 8
b10 9
b11 :
b100 ;
b101 <
b110 =
b111 >
b1000 ?
b1001 @
b0 A
b1 B
b10 C
b11 D
b100 E
b101 F
b110 G
b111 H
b0 I
b1 J
b10 K
b11 L
b100 M
b11111111111111111111111111111111 N
bx O
bx P
bx Q
xR
xS
bx T
b0 U
bx V
xW
xX
xY
bx Z
x[
x\
x]
bx ^
bx _
bx `
xa
xb
xc
bx d
bx e
xf
xg
xh
bx i
xj
xk
bx l
xm
bx n
xo
bx p
xq
xr
xs
bx t
xu
bx v
bx w
bx x
bx y
bx z
bx {
bx |
bx }
bx ~
bx !!
bx "!
$end
#1
b1 U
#2
b10 U
#3
b11 U
#4
b100 U
#5
b101 U
#6
b110 U
#7
b111 U
#8
b1000 U
#9
b1001 U
#10
b1010 U
#11
b1011 U
#12
b1100 U
#13
b1101 U
#14
b1110 U
#15
b1111 U
#16
b10000 U
#17
b10001 U
#18
b10010 U
#19
b10011 U
#20
b10100 U
#21
b10101 U
#22
b10110 U
#23
b10111 U
#24
b11000 U
#25
b11001 U
#26
b11010 U
#27
b11011 U
#28
b11100 U
#29
b11101 U
#30
b11110 U
#31
b11111 U
#32
b100000 U
#33
b100001 U
#34
b100010 U
#35
b100011 U
#36
b100100 U
#37
b100101 U
#38
b100110 U
#39
b100111 U
#40
b101000 U
#41
b101001 U
#42
b101010 U
#43
b101011 U
#44
b101100 U
#45
b101101 U
#46
b101110 U
#47
b101111 U
#48
b110000 U
#49
b110001 U
#50
b110010 U
#51
b110011 U
#52
b110100 U
#53
b110101 U
#54
b110110 U
#55
b110111 U
#56
b111000 U
#57
b111001 U
#58
b111010 U
#59
b111011 U
#60
b111100 U
#61
b111101 U
#62
b111110 U
#63
b111111 U
#64
b1000000 U
#65
b1000001 U
#66
b1000010 U
#67
b1000011 U
#68
b1000100 U
#69
b1000101 U
#70
b1000110 U
#71
b1000111 U
#72
b1001000 U
#73
b1001001 U
#74
b1001010 U
#75
b1001011 U
#76
b1001100 U
#77
b1001101 U
#78
b1001110 U
#79
b1001111 U
#80
b1010000 U
#81
b1010001 U
#82
b1010010 U
#83
b1010011 U
#84
b1010100 U
#85
b1010101 U
#86
b1010110 U
#87
b1010111 U
#88
b1011000 U
#89
b1011001 U
#90
b1011010 U
#91
b1011011 U
#92
b1011100 U
#93
b1011101 U
#94
b1011110 U
#95
b1011111 U
#96
b1100000 U
#97
b1100001 U
#98
b1100010 U
#99
b1100011 U
#100
b1100100 U
#101
b1100101 U
#102
b1100110 U
#103
b1100111 U
#104
b1101000 U
#105
b1101001 U
#106
b1101010 U
#107
b1101011 U
#108
b1101100 U
#109
b1101101 U
#110
b1101110 U
#111
b1101111 U
#112
b1110000 U
#113
b1110001 U
#114
b1110010 U
#115
b1110011 U
#116
b1110100 U
#117
b1110101 U
#118
b1110110 U
#119
b1110111 U
#120
b1111000 U
#121
b1111001 U
#122
b1111010 U
#123
b1111011 U
#124
b1111100 U
#125
b1111101 U
#126
b1111110 U
#127
b1111111 U
#128
b10000000 U
#129
b10000001 U
#130
b10000010 U
#131
b10000011 U
#132
b10000100 U
#133
b10000101 U
#134
b10000110 U
#135
b10000111 U
#136
b10001000 U
#137
b10001001 U
#138
b10001010 U
#139
b10001011 U
#140
b10001100 U
#141
b10001101 U
#142
b10001110 U
#143
b10001111 U
#144
b10010000 U
#145
b10010001 U
#146
b10010010 U
#147
b10010011 U
#148
b10010100 U
#149
b10010101 U
#150
b10010110 U
#151
b10010111 U
#152
b10011000 U
#153
b10011001 U
#154
b10011010 U
#155
b10011011 U
#156
b10011100 U
#157
b10011101 U
#158
b10011110 U
#159
b10011111 U
#160
b10100000 U
#161
b10100001 U
#162
b10100010 U
#163
b10100011 U
#164
b10100100 U
#165
b10100101 U
#166
b10100110 U
#167
b10100111 U
#168
b10101000 U
#169
b10101001 U
#170
b10101010 U
#171
b10101011 U
#172
b10101100 U
#173
b10101101 U
#174
b10101110 U
#175
b10101111 U
#176
b10110000 U
#177
b10110001 U
#178
b10110010 U
#179
b10110011 U
#180
b10110100 U
#181
b10110101 U
#182
b10110110 U
#183
b10110111 U
#184
b10111000 U
#185
b10111001 U
#186
b10111010 U
#187
b10111011 U
#188
b10111100 U
#189
b10111101 U
#190
b10111110 U
#191
b10111111 U
#192
b11000000 U
#193
b11000001 U
#194
b11000010 U
#195
b11000011 U
#196
b11000100 U
#197
b11000101 U
#198
b11000110 U
#199
b11000111 U
#200
b11001000 U
#201
b11001001 U
#202
b11001010 U
#203
b11001011 U
#204
b11001100 U
#205
b11001101 U
#206
b11001110 U
#207
b11001111 U
#208
b11010000 U
#209
b11010001 U
#210
b11010010 U
#211
b11010011 U
#212
b11010100 U
#213
b11010101 U
#214
b11010110 U
#215
b11010111 U
#216
b11011000 U
#217
b11011001 U
#218
b11011010 U
#219
b11011011 U
#220
b11011100 U
#221
b11011101 U
#222
b11011110 U
#223
b11011111 U
#224
b11100000 U
#225
b11100001 U
#226
b11100010 U
#227
b11100011 U
#228
b11100100 U
#229
b11100101 U
#230
b11100110 U
#231
b11100111 U
#232
b11101000 U
#233
b11101001 U
#234
b11101010 U
#235
b11101011 U
#236
b11101100 U
#237
b11101101 U
#238
b11101110 U
#239
b11101111 U
#240
b11110000 U
#241
b11110001 U
#242
b11110010 U
#243
b11110011 U
#244
b11110100 U
#245
b11110101 U
#246
b11110110 U
#247
b11110111 U
#248
b11111000 U
#249
b11111001 U
#250
b11111010 U
#251
b11111011 U
#252
b11111100 U
#253
b11111101 U
#254
b11111110 U
#255
b11111111 U
#256
b100000000 U
#257
b100000001 U
#258
b100000010 U
#259
b100000011 U
#260
b100000100 U
#261
b100000101 U
#262
b100000110 U
#263
b100000111 U
#264
b100001000 U
#265
b100001001 U
#266
b100001010 U
#267
b100001011 U
#268
b100001100 U
#269
b100001101 U
#270
b100001110 U
#271
b100001111 U
#272
b100010000 U
#273
b100010001 U
#274
b100010010 U
#275
b100010011 U
#276
b100010100 U
#277
b100010101 U
#278
b100010110 U
#279
b100010111 U
#280
b100011000 U
#281
b100011001 U
#282
b100011010 U
#283
b100011011 U
#284
b100011100 U
#285
b100011101 U
#286
b100011110 U
#287
b100011111 U
#288
b100100000 U
#289
b100100001 U
#290
b100100010 U
#291
b100100011 U
#292
b100100100 U
#293
b100100101 U
#294
b100100110 U
#295
b100100111 U
#296
b100101000 U
#297
b100101001 U
#298
b100101010 U
#299
b100101011 U
#300
b100101100 U
#301
b100101101 U
#302
b100101110 U
#303
b100101111 U
#304
b100110000 U
#305
b100110001 U
#306
b100110010 U
#307
b100110011 U
#308
b100110100 U
#309
b100110101 U
#310
b100110110 U
#311
b100110111 U
#312
b100111000 U
#313
b100111001 U
#314
b100111010 U
#315
b100111011 U
#316
b100111100 U
#317
b100111101 U
#318
b100111110 U
#319
b100111111 U
#320
b101000000 U
#321
b101000001 U
#322
b101000010 U
#323
b101000011 U
#324
b101000100 U
#325
b101000101 U
#326
b101000110 U
#327
b101000111 U
#328
b101001000 U
#329
b101001001 U
#330
b101001010 U
#331
b101001011 U
#332
b101001100 U
#333
b101001101 U
#334
b101001110 U
#335
b101001111 U
#336
b101010000 U
#337
b101010001 U
#338
b101010010 U
#339
b101010011 U
#340
b101010100 U
#341
b101010101 U
#342
b101010110 U
#343
b101010111 U
